{
  "identifier": "",
  "motion_text": "Judiciary",
  "motion_classification": [
    "passage"
  ],
  "start_date": "2025-02-19",
  "result": "fail",
  "organization": "~{\"classification\": \"upper\"}",
  "legislative_session": "2025",
  "bill": "8815f15e-b150-11f0-98dc-5ae41c099e76",
  "bill_action": null,
  "bill_identifier": "SB829",
  "votes": [
    {
      "option": "yes",
      "voter_name": "Jett",
      "voter_id": "~{\"name\": \"Jett\"}",
      "note": ""
    },
    {
      "option": "yes",
      "voter_name": "Standridge",
      "voter_id": "~{\"name\": \"Standridge\"}",
      "note": ""
    },
    {
      "option": "no",
      "voter_name": "Boren",
      "voter_id": "~{\"name\": \"Boren\"}",
      "note": ""
    },
    {
      "option": "no",
      "voter_name": "Brooks",
      "voter_id": "~{\"name\": \"Brooks\"}",
      "note": ""
    },
    {
      "option": "no",
      "voter_name": "Gollihare",
      "voter_id": "~{\"name\": \"Gollihare\"}",
      "note": ""
    },
    {
      "option": "no",
      "voter_name": "Howard",
      "voter_id": "~{\"name\": \"Howard\"}",
      "note": ""
    },
    {
      "option": "no",
      "voter_name": "Jech",
      "voter_id": "~{\"name\": \"Jech\"}",
      "note": ""
    },
    {
      "option": "no",
      "voter_name": "Rosino",
      "voter_id": "~{\"name\": \"Rosino\"}",
      "note": ""
    }
  ],
  "counts": [
    {
      "option": "yes",
      "value": 2
    },
    {
      "option": "no",
      "value": 6
    },
    {
      "option": "other",
      "value": 0
    }
  ],
  "sources": [
    {
      "url": "https://www.oklegislature.gov/cf/2025-26%20SUPPORT%20DOCUMENTS/votes/Senate/SB829_VOTES.HTM",
      "note": ""
    }
  ],
  "extras": {},
  "dedupe_key": "https://www.oklegislature.gov/cf/2025-26%20SUPPORT%20DOCUMENTS/votes/Senate/SB829_VOTES.HTM#12"
}