{
  "legislative_session": "2025",
  "identifier": "HB1727",
  "title": "Higher education; Oklahoma Higher Learning Access Program; eligibility for children of certain teachers; effective date; emergency.",
  "from_organization": "~{\"classification\": \"lower\"}",
  "classification": [
    "bill"
  ],
  "subject": [],
  "abstracts": [],
  "other_titles": [],
  "other_identifiers": [],
  "actions": [
    {
      "description": "First Reading",
      "date": "2025-02-03",
      "organization_id": "~{\"classification\": \"lower\"}",
      "classification": [
        "introduction",
        "reading-1"
      ],
      "related_entities": [],
      "_processing": {
        "log_file_created": "2025-10-25T03:55:54Z"
      }
    },
    {
      "description": "Authored by Representative Moore",
      "date": "2025-02-03",
      "organization_id": "~{\"classification\": \"lower\"}",
      "classification": [],
      "related_entities": [],
      "_processing": {
        "log_file_created": "2025-10-25T03:55:54Z"
      }
    },
    {
      "description": "Second Reading referred to Appropriations and Budget",
      "date": "2025-02-04",
      "organization_id": "~{\"classification\": \"lower\"}",
      "classification": [
        "reading-2",
        "referral-committee"
      ],
      "related_entities": [],
      "_processing": {
        "log_file_created": "2025-10-25T03:55:54Z"
      }
    },
    {
      "description": "CR; Do Pass, amended by committee substitute Appropriations and Budget Committee",
      "date": "2025-02-26",
      "organization_id": "~{\"classification\": \"lower\"}",
      "classification": [
        "committee-passage"
      ],
      "related_entities": [],
      "_processing": {
        "log_file_created": "2025-10-25T03:55:54Z"
      }
    },
    {
      "description": "Coauthored by Representative(s) McCane, Munson, Provenzano",
      "date": "2025-02-26",
      "organization_id": "~{\"classification\": \"lower\"}",
      "classification": [],
      "related_entities": [],
      "_processing": {
        "log_file_created": "2025-10-25T03:55:54Z"
      }
    },
    {
      "description": "General Order",
      "date": "2025-03-06",
      "organization_id": "~{\"classification\": \"lower\"}",
      "classification": [],
      "related_entities": [],
      "_processing": {
        "log_file_created": "2025-10-25T03:55:54Z"
      }
    },
    {
      "description": "Coauthored by Representative(s) Hill, Harris, Deck, Archer, West (Tammy), Gise",
      "date": "2025-03-06",
      "organization_id": "~{\"classification\": \"lower\"}",
      "classification": [],
      "related_entities": [],
      "_processing": {
        "log_file_created": "2025-10-25T03:55:54Z"
      }
    },
    {
      "description": "Authored by Senator Pugh (principal Senate author)",
      "date": "2025-03-06",
      "organization_id": "~{\"classification\": \"lower\"}",
      "classification": [],
      "related_entities": [],
      "_processing": {
        "log_file_created": "2025-10-25T03:55:54Z"
      }
    },
    {
      "description": "Amended",
      "date": "2025-03-06",
      "organization_id": "~{\"classification\": \"lower\"}",
      "classification": [
        "amendment-passage"
      ],
      "related_entities": [],
      "_processing": {
        "log_file_created": "2025-10-25T03:55:54Z"
      }
    },
    {
      "description": "Title stricken",
      "date": "2025-03-06",
      "organization_id": "~{\"classification\": \"lower\"}",
      "classification": [],
      "related_entities": [],
      "_processing": {
        "log_file_created": "2025-10-25T03:55:54Z"
      }
    },
    {
      "description": "Third Reading, Measure and Emergency passed:  Ayes: 71 Nays: 20",
      "date": "2025-03-06",
      "organization_id": "~{\"classification\": \"lower\"}",
      "classification": [
        "passage",
        "reading-3"
      ],
      "related_entities": [],
      "_processing": {
        "log_file_created": "2025-10-25T03:55:54Z"
      }
    },
    {
      "description": "Referred for engrossment",
      "date": "2025-03-06",
      "organization_id": "~{\"classification\": \"lower\"}",
      "classification": [],
      "related_entities": [],
      "_processing": {
        "log_file_created": "2025-10-25T03:55:54Z"
      }
    },
    {
      "description": "Engrossed, signed, to Senate",
      "date": "2025-03-10",
      "organization_id": "~{\"classification\": \"lower\"}",
      "classification": [
        "passage"
      ],
      "related_entities": [],
      "_processing": {
        "log_file_created": "2025-10-25T03:55:54Z"
      }
    },
    {
      "description": "First Reading",
      "date": "2025-03-10",
      "organization_id": "~{\"classification\": \"upper\"}",
      "classification": [
        "introduction",
        "reading-1"
      ],
      "related_entities": [],
      "_processing": {
        "log_file_created": "2025-10-25T03:55:54Z"
      }
    },
    {
      "description": "Coauthored by Representative Alonso-Sandoval",
      "date": "2025-03-10",
      "organization_id": "~{\"classification\": \"upper\"}",
      "classification": [],
      "related_entities": [],
      "_processing": {
        "log_file_created": "2025-10-25T03:55:54Z"
      }
    },
    {
      "description": "Coauthored by Representative Ranson",
      "date": "2025-03-11",
      "organization_id": "~{\"classification\": \"upper\"}",
      "classification": [],
      "related_entities": [],
      "_processing": {
        "log_file_created": "2025-10-25T03:55:54Z"
      }
    },
    {
      "description": "Coauthored by Representative Waldron",
      "date": "2025-03-11",
      "organization_id": "~{\"classification\": \"upper\"}",
      "classification": [],
      "related_entities": [],
      "_processing": {
        "log_file_created": "2025-10-25T03:55:54Z"
      }
    },
    {
      "description": "Coauthored by Representative Rosecrants",
      "date": "2025-03-11",
      "organization_id": "~{\"classification\": \"upper\"}",
      "classification": [],
      "related_entities": [],
      "_processing": {
        "log_file_created": "2025-10-25T03:55:54Z"
      }
    },
    {
      "description": "Coauthored by Representative Wolfley",
      "date": "2025-03-11",
      "organization_id": "~{\"classification\": \"upper\"}",
      "classification": [],
      "related_entities": [],
      "_processing": {
        "log_file_created": "2025-10-25T03:55:54Z"
      }
    },
    {
      "description": "Coauthored by Senator Pederson",
      "date": "2025-03-12",
      "organization_id": "~{\"classification\": \"upper\"}",
      "classification": [],
      "related_entities": [],
      "_processing": {
        "log_file_created": "2025-10-25T03:55:54Z"
      }
    },
    {
      "description": "Second Reading referred to Education Committee then to Appropriations Committee",
      "date": "2025-04-01",
      "organization_id": "~{\"classification\": \"upper\"}",
      "classification": [
        "reading-2",
        "referral-committee"
      ],
      "related_entities": [],
      "_processing": {
        "log_file_created": "2025-10-25T03:55:54Z"
      }
    },
    {
      "description": "Reported Do Pass as amended Education committee; CR filed",
      "date": "2025-04-08",
      "organization_id": "~{\"classification\": \"upper\"}",
      "classification": [
        "committee-passage"
      ],
      "related_entities": [],
      "_processing": {
        "log_file_created": "2025-10-25T03:55:54Z"
      }
    },
    {
      "description": "Enacting clause stricken",
      "date": "2025-04-08",
      "organization_id": "~{\"classification\": \"upper\"}",
      "classification": [],
      "related_entities": [],
      "_processing": {
        "log_file_created": "2025-10-25T03:55:54Z"
      }
    },
    {
      "description": "Referred to Appropriations",
      "date": "2025-04-08",
      "organization_id": "~{\"classification\": \"upper\"}",
      "classification": [
        "referral-committee"
      ],
      "related_entities": [],
      "_processing": {
        "log_file_created": "2025-10-25T03:55:54Z"
      }
    },
    {
      "description": "Coauthored by Senator Hicks",
      "date": "2025-04-08",
      "organization_id": "~{\"classification\": \"upper\"}",
      "classification": [],
      "related_entities": [],
      "_processing": {
        "log_file_created": "2025-10-25T03:55:54Z"
      }
    },
    {
      "description": "Coauthored by Senator Mann",
      "date": "2025-04-09",
      "organization_id": "~{\"classification\": \"upper\"}",
      "classification": [],
      "related_entities": [],
      "_processing": {
        "log_file_created": "2025-10-25T03:55:54Z"
      }
    },
    {
      "description": "Coauthored by Representative Townley",
      "date": "2025-04-21",
      "organization_id": "~{\"classification\": \"upper\"}",
      "classification": [],
      "related_entities": [],
      "_processing": {
        "log_file_created": "2025-10-25T03:55:54Z"
      }
    },
    {
      "description": "Reported Do Pass, amended by committee substitute Appropriations committee; CR filed",
      "date": "2025-04-23",
      "organization_id": "~{\"classification\": \"upper\"}",
      "classification": [
        "committee-passage"
      ],
      "related_entities": [],
      "_processing": {
        "log_file_created": "2025-10-25T03:55:54Z"
      }
    },
    {
      "description": "Placed on General Order",
      "date": "2025-04-28",
      "organization_id": "~{\"classification\": \"upper\"}",
      "classification": [],
      "related_entities": [],
      "_processing": {
        "log_file_created": "2025-10-25T03:55:54Z"
      }
    },
    {
      "description": "General Order, Amended by Floor Substitute",
      "date": "2025-05-08",
      "organization_id": "~{\"classification\": \"upper\"}",
      "classification": [],
      "related_entities": [],
      "_processing": {
        "log_file_created": "2025-10-25T03:55:54Z"
      }
    },
    {
      "description": "Measure and Emergency passed:  Ayes:  38 Nays:  5",
      "date": "2025-05-08",
      "organization_id": "~{\"classification\": \"upper\"}",
      "classification": [
        "passage"
      ],
      "related_entities": [],
      "_processing": {
        "log_file_created": "2025-10-25T03:55:54Z"
      }
    },
    {
      "description": "Referred for engrossment",
      "date": "2025-05-08",
      "organization_id": "~{\"classification\": \"upper\"}",
      "classification": [],
      "related_entities": [],
      "_processing": {
        "log_file_created": "2025-10-25T03:55:54Z"
      }
    },
    {
      "description": "Engrossed to House",
      "date": "2025-05-12",
      "organization_id": "~{\"classification\": \"upper\"}",
      "classification": [
        "passage"
      ],
      "related_entities": [],
      "_processing": {
        "log_file_created": "2025-10-25T03:55:54Z"
      }
    },
    {
      "description": "SA's received",
      "date": "2025-05-12",
      "organization_id": "~{\"classification\": \"lower\"}",
      "classification": [],
      "related_entities": [],
      "_processing": {
        "log_file_created": "2025-10-25T03:55:54Z"
      }
    },
    {
      "description": "SA's rejected, conference requested, conferees to be named later",
      "date": "2025-05-14",
      "organization_id": "~{\"classification\": \"lower\"}",
      "classification": [],
      "related_entities": [],
      "_processing": {
        "log_file_created": "2025-10-25T03:55:54Z"
      }
    },
    {
      "description": "HC's named: GCCA",
      "date": "2025-05-15",
      "organization_id": "~{\"classification\": \"lower\"}",
      "classification": [],
      "related_entities": [],
      "_processing": {
        "log_file_created": "2025-10-25T03:55:54Z"
      }
    },
    {
      "description": "Conference granted, GCCA",
      "date": "2025-05-15",
      "organization_id": "~{\"classification\": \"upper\"}",
      "classification": [],
      "related_entities": [],
      "_processing": {
        "log_file_created": "2025-10-25T03:55:54Z"
      }
    },
    {
      "description": "CCR submitted",
      "date": "2025-05-27",
      "organization_id": "~{\"classification\": \"lower\"}",
      "classification": [],
      "related_entities": [],
      "_processing": {
        "log_file_created": "2025-10-25T03:55:54Z"
      }
    },
    {
      "description": "Coauthored by Representative(s) Pogemiller, Hasenbeck",
      "date": "2025-05-27",
      "organization_id": "~{\"classification\": \"lower\"}",
      "classification": [],
      "related_entities": [],
      "_processing": {
        "log_file_created": "2025-10-25T03:55:54Z"
      }
    },
    {
      "description": "Title restored",
      "date": "2025-05-27",
      "organization_id": "~{\"classification\": \"lower\"}",
      "classification": [],
      "related_entities": [],
      "_processing": {
        "log_file_created": "2025-10-25T03:55:54Z"
      }
    },
    {
      "description": "Enacting clause restored",
      "date": "2025-05-27",
      "organization_id": "~{\"classification\": \"lower\"}",
      "classification": [],
      "related_entities": [],
      "_processing": {
        "log_file_created": "2025-10-25T03:55:54Z"
      }
    },
    {
      "description": "CCR adopted",
      "date": "2025-05-28",
      "organization_id": "~{\"classification\": \"lower\"}",
      "classification": [],
      "related_entities": [],
      "_processing": {
        "log_file_created": "2025-10-25T03:55:54Z"
      }
    },
    {
      "description": "Fourth Reading, Measure and Emergency Passed:  Ayes: 60  Nays: 27; Ayes: 69 Nays: 20",
      "date": "2025-05-28",
      "organization_id": "~{\"classification\": \"lower\"}",
      "classification": [
        "passage"
      ],
      "related_entities": [],
      "_processing": {
        "log_file_created": "2025-10-25T03:55:54Z"
      }
    },
    {
      "description": "To Senate",
      "date": "2025-05-28",
      "organization_id": "~{\"classification\": \"lower\"}",
      "classification": [],
      "related_entities": [],
      "_processing": {
        "log_file_created": "2025-10-25T03:55:54Z"
      }
    },
    {
      "description": "CCR read, GCCA",
      "date": "2025-05-28",
      "organization_id": "~{\"classification\": \"upper\"}",
      "classification": [],
      "related_entities": [],
      "_processing": {
        "log_file_created": "2025-10-25T03:55:54Z"
      }
    },
    {
      "description": "CCR adopted, GCCA",
      "date": "2025-05-28",
      "organization_id": "~{\"classification\": \"upper\"}",
      "classification": [],
      "related_entities": [],
      "_processing": {
        "log_file_created": "2025-10-25T03:55:54Z"
      }
    },
    {
      "description": "Measure passed, to House:  Ayes: 35  Nays: 10",
      "date": "2025-05-28",
      "organization_id": "~{\"classification\": \"upper\"}",
      "classification": [
        "passage"
      ],
      "related_entities": [],
      "_processing": {
        "log_file_created": "2025-10-25T03:55:54Z"
      }
    },
    {
      "description": "Emergency passed:  Ayes: 42 Nays: 2",
      "date": "2025-05-28",
      "organization_id": "~{\"classification\": \"upper\"}",
      "classification": [],
      "related_entities": [],
      "_processing": {
        "log_file_created": "2025-10-25T03:55:54Z"
      }
    },
    {
      "description": "Referred for enrollment",
      "date": "2025-05-28",
      "organization_id": "~{\"classification\": \"lower\"}",
      "classification": [],
      "related_entities": [],
      "_processing": {
        "log_file_created": "2025-10-25T03:55:54Z"
      }
    },
    {
      "description": "Enrolled, signed, to Senate",
      "date": "2025-05-28",
      "organization_id": "~{\"classification\": \"lower\"}",
      "classification": [],
      "related_entities": [],
      "_processing": {
        "log_file_created": "2025-10-25T03:55:54Z"
      }
    },
    {
      "description": "Enrolled measure signed, returned to House",
      "date": "2025-05-28",
      "organization_id": "~{\"classification\": \"upper\"}",
      "classification": [],
      "related_entities": [],
      "_processing": {
        "log_file_created": "2025-10-25T03:55:54Z"
      }
    },
    {
      "description": "Sent to Governor",
      "date": "2025-05-28",
      "organization_id": "~{\"classification\": \"lower\"}",
      "classification": [
        "executive-receipt"
      ],
      "related_entities": [],
      "_processing": {
        "log_file_created": "2025-10-25T03:55:54Z"
      }
    },
    {
      "description": "Approved by Governor 06/10/2025",
      "date": "2025-05-30",
      "organization_id": "~{\"classification\": \"lower\"}",
      "classification": [
        "executive-signature"
      ],
      "related_entities": [],
      "_processing": {
        "log_file_created": "2025-10-25T03:55:54Z"
      }
    }
  ],
  "sponsorships": [
    {
      "name": "Moore",
      "classification": "primary",
      "entity_type": "person",
      "primary": true,
      "person_id": "~{\"name\": \"Moore\"}",
      "organization_id": null
    },
    {
      "name": "Pugh",
      "classification": "primary",
      "entity_type": "person",
      "primary": true,
      "person_id": "~{\"name\": \"Pugh\"}",
      "organization_id": null
    }
  ],
  "related_bills": [],
  "versions": [
    {
      "note": "Introduced",
      "links": [
        {
          "url": "https://www.oklegislature.gov/cf_pdf/2025-26 INT/hB/HB1727 INT.PDF",
          "media_type": "application/pdf"
        }
      ],
      "date": "",
      "classification": ""
    },
    {
      "note": "House Committee Substitute",
      "links": [
        {
          "url": "https://www.oklegislature.gov/cf_pdf/2025-26 COMMITTEE SUBS/HCS/HB1727 CS.PDF",
          "media_type": "application/pdf"
        }
      ],
      "date": "",
      "classification": ""
    },
    {
      "note": "Senate Committee Substitute for House Bill",
      "links": [
        {
          "url": "https://www.oklegislature.gov/cf_pdf/2025-26 COMMITTEE SUBS/SCSH/HB1727 SCSH.PDF",
          "media_type": "application/pdf"
        }
      ],
      "date": "",
      "classification": ""
    },
    {
      "note": "Floor (House)",
      "links": [
        {
          "url": "https://www.oklegislature.gov/cf_pdf/2025-26 FLR/HFLR/HB1727 HFLR.PDF",
          "media_type": "application/pdf"
        }
      ],
      "date": "",
      "classification": ""
    },
    {
      "note": "Floor (Senate)",
      "links": [
        {
          "url": "https://www.oklegislature.gov/cf_pdf/2025-26 FLR/SFLR/HB1727 SFLR.PDF",
          "media_type": "application/pdf"
        }
      ],
      "date": "",
      "classification": ""
    },
    {
      "note": "Engrossed",
      "links": [
        {
          "url": "https://www.oklegislature.gov/cf_pdf/2025-26 ENGR/hB/HB1727 ENGR.PDF",
          "media_type": "application/pdf"
        }
      ],
      "date": "",
      "classification": ""
    },
    {
      "note": "Amended And Engrossed",
      "links": [
        {
          "url": "https://www.oklegislature.gov/cf_pdf/2025-26 AMENDMENTS/Amendment and Engr/HB1727 SAHB AND ENGR.PDF",
          "media_type": "application/pdf"
        }
      ],
      "date": "",
      "classification": ""
    },
    {
      "note": "House Conference Committee Substitute",
      "links": [
        {
          "url": "https://www.oklegislature.gov/cf_pdf/2025-26 COMMITTEE SUBS/HCCS/HB1727 CCS.PDF",
          "media_type": "application/pdf"
        }
      ],
      "date": "",
      "classification": ""
    },
    {
      "note": "Enrolled (final version)",
      "links": [
        {
          "url": "https://www.oklegislature.gov/cf_pdf/2025-26 ENR/hB/HB1727 ENR.PDF",
          "media_type": "application/pdf"
        }
      ],
      "date": "",
      "classification": ""
    },
    {
      "note": "HB1727 (5-05-25) (PUGH) FS FA1.PDF",
      "links": [
        {
          "url": "https://www.oklegislature.gov/cf_pdf/2025-26 FLOOR AMENDMENTS/Senate/HB1727 (5-05-25) (PUGH) FS FA1.PDF",
          "media_type": "application/pdf"
        }
      ],
      "date": "",
      "classification": ""
    },
    {
      "note": "1 Floor Amendment by KANE",
      "links": [
        {
          "url": "https://www.oklegislature.gov/cf_pdf/2025-26 FLOOR AMENDMENTS/House/HB1727 FA1 KANEJO-CC.PDF",
          "media_type": "application/pdf"
        }
      ],
      "date": "",
      "classification": ""
    },
    {
      "note": "Committee Amendment",
      "links": [
        {
          "url": "https://www.oklegislature.gov/cf_pdf/2025-26 COMMITTEE AMENDMENTS/Senate/HB1727 PCS.PDF",
          "media_type": "application/pdf"
        }
      ],
      "date": "",
      "classification": ""
    },
    {
      "note": "Committee Amendment 1",
      "links": [
        {
          "url": "https://www.oklegislature.gov/cf_pdf/2025-26 COMMITTEE AMENDMENTS/House/HB1727 FULLAMD1 ANTHONY MOORE-AQH.PDF",
          "media_type": "application/pdf"
        }
      ],
      "date": "",
      "classification": ""
    }
  ],
  "documents": [
    {
      "note": "House Committee Report",
      "links": [
        {
          "url": "https://www.oklegislature.gov/cf_pdf/2025-26 COMMITTEE REPORTS/HOUSE/HB1727 HCR.PDF",
          "media_type": "application/pdf"
        }
      ],
      "date": "",
      "classification": ""
    },
    {
      "note": "Senate Committee Report 1",
      "links": [
        {
          "url": "https://www.oklegislature.gov/cf_pdf/2025-26 COMMITTEE REPORTS/SENATE/HB1727 SCRDR1.PDF",
          "media_type": "application/pdf"
        }
      ],
      "date": "",
      "classification": ""
    },
    {
      "note": "Senate Committee Report 2",
      "links": [
        {
          "url": "https://www.oklegislature.gov/cf_pdf/2025-26 COMMITTEE REPORTS/SENATE/HB1727 SCRDR2.PDF",
          "media_type": "application/pdf"
        }
      ],
      "date": "",
      "classification": ""
    },
    {
      "note": "Scheduled House CCR 1(A)",
      "links": [
        {
          "url": "https://www.oklegislature.gov/cf_pdf/2025-26 SUPPORT DOCUMENTS/SCHEDULED CCR/House/HB1727 CCR A.PDF",
          "media_type": "application/pdf"
        }
      ],
      "date": "",
      "classification": ""
    },
    {
      "note": "House Conference Committee Report",
      "links": [
        {
          "url": "https://www.oklegislature.gov/cf_pdf/2025-26 COMMITTEE REPORTS/House/CCR Combined/HB1727 CCR.PDF",
          "media_type": "application/pdf"
        }
      ],
      "date": "",
      "classification": ""
    }
  ],
  "citations": [],
  "sources": [
    {
      "url": "http://www.oklegislature.gov/BillInfo.aspx?Bill=HB1727&session=2500",
      "note": ""
    }
  ],
  "extras": {},
  "jurisdiction": {
    "id": "ocd-jurisdiction/country:us/state:ok/government",
    "name": "Oklahoma",
    "classification": "state",
    "division_id": "ocd-division/country:us/state:ok"
  },
  "_processing": {
    "logs_latest_update": "2025-10-25T03:55:54Z",
    "text_extraction_latest_update": "2025-10-29T16:06:40.947968Z"
  }
}