{
  "legislative_session": "2025",
  "identifier": "SR10",
  "title": "Resolution; declaring April 22, 2025 as Oklahoma Agriculture Day; recognizing and celebrating agriculture's impact on our state's heritage and economy.",
  "from_organization": "~{\"classification\": \"upper\"}",
  "classification": [
    "resolution"
  ],
  "subject": [],
  "abstracts": [],
  "other_titles": [],
  "other_identifiers": [],
  "actions": [
    {
      "description": "First Reading",
      "date": "2025-03-31",
      "organization_id": "~{\"classification\": \"upper\"}",
      "classification": [
        "introduction",
        "reading-1"
      ],
      "related_entities": [],
      "_processing": {
        "log_file_created": "2025-10-25T03:55:58Z"
      }
    },
    {
      "description": "Authored by Senator Murdock",
      "date": "2025-03-31",
      "organization_id": "~{\"classification\": \"upper\"}",
      "classification": [],
      "related_entities": [],
      "_processing": {
        "log_file_created": "2025-10-25T03:55:58Z"
      }
    },
    {
      "description": "Direct to Calendar",
      "date": "2025-04-22",
      "organization_id": "~{\"classification\": \"upper\"}",
      "classification": [],
      "related_entities": [],
      "_processing": {
        "log_file_created": "2025-10-25T03:55:58Z"
      }
    },
    {
      "description": "Considered",
      "date": "2025-04-22",
      "organization_id": "~{\"classification\": \"upper\"}",
      "classification": [],
      "related_entities": [],
      "_processing": {
        "log_file_created": "2025-10-25T03:55:58Z"
      }
    },
    {
      "description": "Adopted, referred for enrollment",
      "date": "2025-04-22",
      "organization_id": "~{\"classification\": \"upper\"}",
      "classification": [
        "passage"
      ],
      "related_entities": [],
      "_processing": {
        "log_file_created": "2025-10-25T03:55:58Z"
      }
    },
    {
      "description": "Enrolled, filed with Secretary of State",
      "date": "2025-04-23",
      "organization_id": "~{\"classification\": \"upper\"}",
      "classification": [],
      "related_entities": [],
      "_processing": {
        "log_file_created": "2025-10-25T03:55:58Z"
      }
    }
  ],
  "sponsorships": [
    {
      "name": "Murdock",
      "classification": "primary",
      "entity_type": "person",
      "primary": true,
      "person_id": "~{\"name\": \"Murdock\"}",
      "organization_id": null
    }
  ],
  "related_bills": [],
  "versions": [
    {
      "note": "Introduced",
      "links": [
        {
          "url": "https://www.oklegislature.gov/cf_pdf/2025-26 INT/SRES/SR10 INT.PDF",
          "media_type": "application/pdf"
        }
      ],
      "date": "",
      "classification": ""
    },
    {
      "note": "Enrolled (final version)",
      "links": [
        {
          "url": "https://www.oklegislature.gov/cf_pdf/2025-26 ENR/SRES/SR10 ENR.PDF",
          "media_type": "application/pdf"
        }
      ],
      "date": "",
      "classification": ""
    }
  ],
  "documents": [],
  "citations": [],
  "sources": [
    {
      "url": "http://www.oklegislature.gov/BillInfo.aspx?Bill=SR10&session=2500",
      "note": ""
    }
  ],
  "extras": {},
  "jurisdiction": {
    "id": "ocd-jurisdiction/country:us/state:ok/government",
    "name": "Oklahoma",
    "classification": "state",
    "division_id": "ocd-division/country:us/state:ok"
  },
  "_processing": {
    "logs_latest_update": "2025-10-25T03:55:58Z"
  }
}