{
  "legislative_session": "2025",
  "identifier": "SB547",
  "title": "Health care; minor self-consent to health services; granting certain protections to parent or legal guardian related to medical records. Effective date.",
  "from_organization": "~{\"classification\": \"upper\"}",
  "classification": [
    "bill"
  ],
  "subject": [],
  "abstracts": [],
  "other_titles": [],
  "other_identifiers": [],
  "actions": [
    {
      "description": "First Reading",
      "date": "2025-02-03",
      "organization_id": "~{\"classification\": \"upper\"}",
      "classification": [
        "introduction",
        "reading-1"
      ],
      "related_entities": [],
      "_processing": {
        "log_file_created": "2025-10-25T03:55:58Z"
      }
    },
    {
      "description": "Authored by Senator Guthrie",
      "date": "2025-02-03",
      "organization_id": "~{\"classification\": \"upper\"}",
      "classification": [],
      "related_entities": [],
      "_processing": {
        "log_file_created": "2025-10-25T03:55:58Z"
      }
    },
    {
      "description": "Second Reading referred to Health and Human Services",
      "date": "2025-02-04",
      "organization_id": "~{\"classification\": \"upper\"}",
      "classification": [
        "reading-2",
        "referral-committee"
      ],
      "related_entities": [],
      "_processing": {
        "log_file_created": "2025-10-25T03:55:58Z"
      }
    },
    {
      "description": "Reported Do Pass, amended by committee substitute Health and Human Services committee; CR filed",
      "date": "2025-02-17",
      "organization_id": "~{\"classification\": \"upper\"}",
      "classification": [
        "committee-passage"
      ],
      "related_entities": [],
      "_processing": {
        "log_file_created": "2025-10-25T03:55:58Z"
      }
    },
    {
      "description": "Title stricken",
      "date": "2025-02-17",
      "organization_id": "~{\"classification\": \"upper\"}",
      "classification": [],
      "related_entities": [],
      "_processing": {
        "log_file_created": "2025-10-25T03:55:58Z"
      }
    },
    {
      "description": "Placed on General Order",
      "date": "2025-02-20",
      "organization_id": "~{\"classification\": \"upper\"}",
      "classification": [],
      "related_entities": [],
      "_processing": {
        "log_file_created": "2025-10-25T03:55:58Z"
      }
    },
    {
      "description": "Coauthored by Senator McIntosh",
      "date": "2025-02-24",
      "organization_id": "~{\"classification\": \"upper\"}",
      "classification": [],
      "related_entities": [],
      "_processing": {
        "log_file_created": "2025-10-25T03:55:58Z"
      }
    },
    {
      "description": "Coauthored by Representative Hall (principal House author)",
      "date": "2025-02-24",
      "organization_id": "~{\"classification\": \"upper\"}",
      "classification": [],
      "related_entities": [],
      "_processing": {
        "log_file_created": "2025-10-25T03:55:58Z"
      }
    },
    {
      "description": "Coauthored by Representative Chapman",
      "date": "2025-03-17",
      "organization_id": "~{\"classification\": \"upper\"}",
      "classification": [],
      "related_entities": [],
      "_processing": {
        "log_file_created": "2025-10-25T03:55:58Z"
      }
    },
    {
      "description": "Coauthored by Senator Hamilton",
      "date": "2025-04-02",
      "organization_id": "~{\"classification\": \"upper\"}",
      "classification": [],
      "related_entities": [],
      "_processing": {
        "log_file_created": "2025-10-25T03:55:58Z"
      }
    }
  ],
  "sponsorships": [
    {
      "name": "Guthrie",
      "classification": "primary",
      "entity_type": "person",
      "primary": true,
      "person_id": "~{\"name\": \"Guthrie\"}",
      "organization_id": null
    },
    {
      "name": "Hall",
      "classification": "primary",
      "entity_type": "person",
      "primary": true,
      "person_id": "~{\"name\": \"Hall\"}",
      "organization_id": null
    }
  ],
  "related_bills": [],
  "versions": [
    {
      "note": "Introduced",
      "links": [
        {
          "url": "https://www.oklegislature.gov/cf_pdf/2025-26 INT/SB/SB547 INT.PDF",
          "media_type": "application/pdf"
        }
      ],
      "date": "",
      "classification": ""
    },
    {
      "note": "Committee Substitute",
      "links": [
        {
          "url": "https://www.oklegislature.gov/cf_pdf/2025-26 COMMITTEE SUBS/SCS/SB547 CS.PDF",
          "media_type": "application/pdf"
        }
      ],
      "date": "",
      "classification": ""
    },
    {
      "note": "Floor (Senate)",
      "links": [
        {
          "url": "https://www.oklegislature.gov/cf_pdf/2025-26 FLR/SFLR/SB547 SFLR.PDF",
          "media_type": "application/pdf"
        }
      ],
      "date": "",
      "classification": ""
    },
    {
      "note": "SB547 (2-27-25) (MCINTOSH) FA1.PDF",
      "links": [
        {
          "url": "https://www.oklegislature.gov/cf_pdf/2025-26 FLOOR AMENDMENTS/Senate/SB547 (2-27-25) (MCINTOSH) FA1.PDF",
          "media_type": "application/pdf"
        }
      ],
      "date": "",
      "classification": ""
    },
    {
      "note": "SB547 (3-04-25) (GUTHRIE) RT FA2.PDF",
      "links": [
        {
          "url": "https://www.oklegislature.gov/cf_pdf/2025-26 FLOOR AMENDMENTS/Senate/SB547 (3-04-25) (GUTHRIE) RT FA2.PDF",
          "media_type": "application/pdf"
        }
      ],
      "date": "",
      "classification": ""
    },
    {
      "note": "Committee Amendment",
      "links": [
        {
          "url": "https://www.oklegislature.gov/cf_pdf/2025-26 COMMITTEE AMENDMENTS/Senate/SB547 PCS.PDF",
          "media_type": "application/pdf"
        }
      ],
      "date": "",
      "classification": ""
    }
  ],
  "documents": [
    {
      "note": "Senate Committee Report",
      "links": [
        {
          "url": "https://www.oklegislature.gov/cf_pdf/2025-26 COMMITTEE REPORTS/SENATE/SB547 SCR.PDF",
          "media_type": "application/pdf"
        }
      ],
      "date": "",
      "classification": ""
    }
  ],
  "citations": [],
  "sources": [
    {
      "url": "http://www.oklegislature.gov/BillInfo.aspx?Bill=SB547&session=2500",
      "note": ""
    }
  ],
  "extras": {},
  "jurisdiction": {
    "id": "ocd-jurisdiction/country:us/state:ok/government",
    "name": "Oklahoma",
    "classification": "state",
    "division_id": "ocd-division/country:us/state:ok"
  },
  "_processing": {
    "logs_latest_update": "2025-10-25T03:55:58Z",
    "text_extraction_latest_update": "2025-10-29T07:21:17.370872Z"
  }
}